lablink_allocator_service/__init__.py
lablink_allocator_service/__main__.py
lablink_allocator_service/conf/__init__.py
lablink_allocator_service/conf/config.yaml
lablink_allocator_service/conf/config.yaml.example
lablink_allocator_service/conf/structured_config.py
lablink_allocator_service/database.py
lablink_allocator_service/generate_init_sql.py
lablink_allocator_service/get_config.py
lablink_allocator_service/lambda_function.py
lablink_allocator_service/main.py
lablink_allocator_service/templates/admin.html
lablink_allocator_service/templates/create-instances.html
lablink_allocator_service/templates/dashboard.html
lablink_allocator_service/templates/delete-dashboard.html
lablink_allocator_service/templates/delete-instances.html
lablink_allocator_service/templates/index.html
lablink_allocator_service/templates/instance-logs.html
lablink_allocator_service/templates/instances.html
lablink_allocator_service/templates/success.html
lablink_allocator_service/utils/__init__.py
lablink_allocator_service/utils/aws_utils.py
lablink_allocator_service/utils/scp.py
lablink_allocator_service/utils/terraform_utils.py
lablink_allocator_service-0.0.2a0.dist-info/WHEEL
lablink_allocator_service-0.0.2a0.dist-info/entry_points.txt
lablink_allocator_service-0.0.2a0.dist-info/METADATA
lablink_allocator_service-0.0.2a0.dist-info/RECORD
