Metadata-Version: 2.3
Name: lablink-allocator-service
Version: 0.0.2a0
Summary: VM Allocator Service Package for Lablink
Author: Elizabeth Berrigan, Talmo Pereira, Andrew Park
Author-email: Elizabeth Berrigan <eberrigan@salk.edu>, Talmo Pereira <talmo@salk.edu>, Andrew Park <hep003@ucsd.edu>
Requires-Dist: flask>=2.2
Requires-Dist: werkzeug>=2.2
Requires-Dist: flask-sqlalchemy>=2.5
Requires-Dist: sqlalchemy>=1.3
Requires-Dist: psycopg2-binary>=2.9
Requires-Dist: hydra-core>=1.3
Requires-Dist: omegaconf>=2.3
Requires-Dist: requests>=2.28
Requires-Dist: flask-httpauth>=4.7
Requires-Dist: boto3>=1.26
Requires-Dist: twine ; extra == 'dev'
Requires-Dist: build ; extra == 'dev'
Requires-Dist: pytest ; extra == 'dev'
Requires-Dist: ruff ; extra == 'dev'
Requires-Dist: pytest-cov ; extra == 'dev'
Requires-Python: >=3.9
Project-URL: Homepage, https://github.com/talmolab/lablink
Project-URL: Issues, https://github.com/talmolab/lablink/issues
Provides-Extra: dev
